LICENSE.md
MANIFEST.in
README.md
setup.py
admin_corporate/__init__.py
admin_corporate/apps.py
admin_corporate/forms.py
admin_corporate/urls.py
admin_corporate/utils.py
admin_corporate/views.py
admin_corporate/static/assets/css/corporate-ui-dashboard.css
admin_corporate/static/assets/css/corporate-ui-dashboard.css.map
admin_corporate/static/assets/css/corporate-ui-dashboard.min.css
admin_corporate/static/assets/css/forms.css
admin_corporate/static/assets/css/nucleo-icons.css
admin_corporate/static/assets/css/nucleo-svg.css
admin_corporate/static/assets/css/widgets.css
admin_corporate/static/assets/fonts/nucleo-icons.eot
admin_corporate/static/assets/fonts/nucleo-icons.svg
admin_corporate/static/assets/fonts/nucleo-icons.ttf
admin_corporate/static/assets/fonts/nucleo-icons.woff
admin_corporate/static/assets/fonts/nucleo-icons.woff2
admin_corporate/static/assets/fonts/nucleo.eot
admin_corporate/static/assets/fonts/nucleo.ttf
admin_corporate/static/assets/fonts/nucleo.woff
admin_corporate/static/assets/fonts/nucleo.woff2
admin_corporate/static/assets/img/3d-cube.png
admin_corporate/static/assets/img/apple-icon.png
admin_corporate/static/assets/img/bg1.jpg
admin_corporate/static/assets/img/bruce-mars.jpg
admin_corporate/static/assets/img/corporate-ui-logo.svg
admin_corporate/static/assets/img/down-arrow-dark.svg
admin_corporate/static/assets/img/down-arrow-white.svg
admin_corporate/static/assets/img/down-arrow.svg
admin_corporate/static/assets/img/favicon.png
admin_corporate/static/assets/img/header-blue-purple.jpg
admin_corporate/static/assets/img/header-orange-purple.jpg
admin_corporate/static/assets/img/icon-calendar.svg
admin_corporate/static/assets/img/icon-clock.svg
admin_corporate/static/assets/img/image-sign-in.jpg
admin_corporate/static/assets/img/image-sign-up.jpg
admin_corporate/static/assets/img/img-1.jpg
admin_corporate/static/assets/img/img-2.jpg
admin_corporate/static/assets/img/img-3.jpg
admin_corporate/static/assets/img/img-4.jpg
django_admin_corporate.egg-info/PKG-INFO
django_admin_corporate.egg-info/SOURCES.txt
django_admin_corporate.egg-info/dependency_links.txt
django_admin_corporate.egg-info/not-zip-safe
django_admin_corporate.egg-info/top_level.txt
